[
  {
    "chapter": "Q",
    "name": "每日政務",
    "stages": [
      { "id": "D-1", "name": "戰爭演習-初" },
      { "id": "D-2", "name": "戰爭演習-中" },
      { "id": "D-3", "name": "戰爭演習-高" },
      { "id": "D-4", "name": "戰爭演習-超" },
      { "id": "D-5", "name": "戰爭演習-特Ⅰ" },
      { "id": "D-6", "name": "戰爭演習-特Ⅱ" },
      { "id": "D-7", "name": "戰爭演習-特Ⅲ" },
      { "id": "D-8", "name": "戰爭演習-特Ⅳ" },
      { "id": "T-1", "name": "商業貿易-初" },
      { "id": "T-2", "name": "商業貿易-中" },
      { "id": "T-3", "name": "商業貿易-高" },
      { "id": "T-4", "name": "商業貿易-超" },
      { "id": "T-5", "name": "商業貿易-特Ⅰ" },
      { "id": "T-6", "name": "商業貿易-特Ⅱ" },
      { "id": "T-7", "name": "商業貿易-特Ⅲ" },
      { "id": "T-8", "name": "商業貿易-特Ⅳ" }
    ]
  },
  {
    "chapter": "S",
    "name": "魔獄塔",
    "stagePrefix": "塔 - ",
    "stageSuffix": ""
  },
  {
    "chapter": "0",
    "name": "序章：魔王凱薩",
    "stages": [
      { "id": "0-1", "name": "凱薩，挺立於大地！" },
      { "id": "0-2", "name": "凱薩，對弱者的教誨！" },
      { "id": "0-3", "name": "凱薩，無雙於戰場！" },
      { "id": "0-4", "name": "凱薩，最強的男人！" },
      { "id": "0-5", "name": "凱薩，不拘小節！" },
      { "id": "0-6", "name": "凱薩，秋風掃落葉！" },
      { "id": "0-6 free", "name": "殘存的叛軍" },
      { "id": "0-7", "name": "凱薩，征服世界！" }
    ]
  },
  {
    "chapter": "1",
    "name": "第一章：巴爾，凱薩來囉",
    "stages": [
      { "id": "1-2", "name": "按門鈴可是禮貌" },
      { "id": "1-3", "name": "款待貴客" },
      { "id": "1-4", "name": "多謝招待" },
      { "id": "1-5", "name": "賭局" },
      { "id": "1-5 free", "name": "荒郊牧場" },
      { "id": "1-6", "name": "下好離手" },
      { "id": "1-6 free", "name": "犬與牛" },
      { "id": "1-7", "name": "道高一尺" },
      { "id": "1-7 free", "name": "潛伏的偵查兵" },
      { "id": "1-8", "name": "魔高一丈" },
      { "id": "1-9", "name": "事情有先後順序" }
    ]
  },
  {
    "chapter": "2",
    "name": "第二章：送上門的聖騎士",
    "stages": [
      { "id": "2-2", "name": "正義的聖光騎士團" },
      { "id": "2-3", "name": "信仰，凱薩教？" },
      { "id": "2-4", "name": "信仰衝突" },
      { "id": "2-5", "name": "聖光女騎士" },
      { "id": "2-5 free", "name": "迷路的聖騎士團" },
      { "id": "2-6", "name": "凱薩的預言" },
      { "id": "2-7", "name": "爛透了" },
      { "id": "2-7 free", "name": "忠犬與騎士" },
      { "id": "2-8", "name": "困獸之鬥" },
      { "id": "2-8 free", "name": "騎士的道具收藏庫" },
      { "id": "2-9", "name": "聖騎士的決意" }
    ]
  },
  {
    "chapter": "3",
    "name": "第三章：貴族的標配是金髮巨乳？",
    "stages": [
      { "id": "3-2", "name": "魔王伊布力斯" },
      { "id": "3-2 free", "name": "魅魔招待所" },
      { "id": "3-3", "name": "愚者的進擊" },
      { "id": "3-4", "name": "小孩子的戰爭" },
      { "id": "3-5", "name": "小手段" },
      { "id": "3-6", "name": "更多的小手段" },
      { "id": "3-6 free", "name": "戰場一隅" },
      { "id": "3-7", "name": "各司其職" },
      { "id": "3-7 free", "name": "伊布力斯軍分隊" },
      { "id": "3-8", "name": "戰鬥的號角" },
      { "id": "3-8 free", "name": "黏呼呼史萊姆天國" },
      { "id": "3-9", "name": "兩軍衝突！" },
      { "id": "3-10", "name": "以魔王之名" }
    ]
  },
  {
    "chapter": "4",
    "name": "第四章：信仰吧！菲歐菈",
    "stages": [
      { "id": "4-2", "name": "進逼的凱薩軍" },
      { "id": "4-3", "name": "零星的抵抗" },
      { "id": "4-3 free-1", "name": "主神教爪子儲藏室" },
      { "id": "4-3 free-2", "name": "主神教金屬儲藏室" },
      { "id": "4-4", "name": "被瓦解的信仰" },
      { "id": "4-5", "name": "對決！聖教軍" },
      { "id": "4-5 free", "name": "主神教水源倉庫" },
      { "id": "4-6", "name": "戰況膠著" },
      { "id": "4-7", "name": "信仰狂熱" },
      { "id": "4-7 free", "name": "主神教儀式倉庫" },
      { "id": "4-8", "name": "突破僵局" },
      { "id": "4-9", "name": "噁心的感覺" },
      { "id": "4-9 free", "name": "主神教粉塵倉庫" },
      { "id": "4-10", "name": "特殊部隊的活躍" },
      { "id": "4-11", "name": "襲來！魔王凱薩" },
      { "id": "4-12", "name": "無益的抵抗" },
      { "id": "4-13", "name": "最後的驅魔結界" }
    ]
  },
  {
    "chapter": "5",
    "name": "第五章：支配者與被支配者",
    "stages": [
      { "id": "5-2", "name": "撒旦軍的突襲" },
      { "id": "5-3", "name": "猝不及防" },
      { "id": "5-4", "name": "撒旦的挑釁" },
      { "id": "5-4 free", "name": "謎之收藏室" },
      { "id": "5-5", "name": "前往戰線" },
      { "id": "5-6", "name": "慾火與鮮血" },
      { "id": "5-6 free", "name": "戰場遺留物" },
      { "id": "5-7", "name": "駐紮點" },
      { "id": "5-8", "name": "追跡，撒旦軍" },
      { "id": "5-9", "name": "過去的糾葛" },
      { "id": "5-9 free", "name": "秘密乳牛天國" },
      { "id": "5-10", "name": "意外的遭遇戰" },
      { "id": "5-11", "name": "狂人與瘋子" },
      { "id": "5-12", "name": "激戰" },
      { "id": "5-13", "name": "熱戰" },
      { "id": "5-14", "name": "征服者與服從者" }
    ]
  },
  {
    "chapter": "6",
    "name": "第六章：傭兵、團長與人妻",
    "stages": [
      { "id": "6-2", "name": "進軍！矮人國！！" },
      { "id": "6-3", "name": "結盟" },
      { "id": "6-3 free", "name": "傭兵金屬收藏庫" },
      { "id": "6-4", "name": "熱情的山脈" },
      { "id": "6-5", "name": "一絲古怪" },
      { "id": "6-6", "name": "釐清頭緒" },
      { "id": "6-6 free", "name": "傭兵狩獵收藏庫" },
      { "id": "6-7", "name": "蒐集！矮人武器" },
      { "id": "6-8", "name": "團長的決斷" },
      { "id": "6-8 free", "name": "傭兵粉塵收藏庫" },
      { "id": "6-9", "name": "且戰且退的傭兵" },
      { "id": "6-10", "name": "斬首作戰" },
      { "id": "6-10 free", "name": "傭兵調和劑收藏庫" },
      { "id": "6-11", "name": "巴爾的指示" },
      { "id": "6-12", "name": "偽裝的攻擊" },
      { "id": "6-13", "name": "斷絕情報" },
      { "id": "6-14", "name": "拉長戰線" },
      { "id": "6-15", "name": "一擊滅蛇" }
    ]
  },
  {
    "chapter": "7",
    "name": "第七章：絕對怪力矮人王",
    "stages": [
      { "id": "7-2", "name": "進軍，矮人國！" },
      { "id": "7-3", "name": "寫作貿易讀作征服" },
      { "id": "7-3 free-1", "name": "矮人的廢棄倉庫" },
      { "id": "7-3 free-2", "name": "矮人的藥劑倉庫" },
      { "id": "7-3 free-3", "name": "矮人的老舊倉庫" },
      { "id": "7-4", "name": "苦勞人、娜娜" },
      { "id": "7-5", "name": "再度發起侵略" },
      { "id": "7-6", "name": "絕對怪力矮人王" },
      { "id": "7-7", "name": "戰略性撤退" },
      { "id": "7-8", "name": "引誘作戰" },
      { "id": "7-9", "name": "逃跑與轉進的差別" },
      { "id": "7-9 free", "name": "矮人的狩獵倉庫" },
      { "id": "7-10", "name": "矮人王的追擊" },
      { "id": "7-11", "name": "正面迎擊" },
      { "id": "7-11 free", "name": "矮人的鍛造倉庫" },
      { "id": "7-12", "name": "左線衝突" },
      { "id": "7-13", "name": "右線衝突" },
      { "id": "7-14", "name": "全線衝突" },
      { "id": "7-15", "name": "魔王vs矮人王" }
    ]
  },
  {
    "chapter": "8",
    "name": "第八章：與公主連結",
    "stages": [
      { "id": "8-2", "name": "風雨欲來" },
      { "id": "8-2 free", "name": "狩獵的茶會" },
      { "id": "8-3", "name": "公主心，法斯情" },
      { "id": "8-4", "name": "零星的遭遇" },
      { "id": "8-5", "name": "斥候的派遣" },
      { "id": "8-6", "name": "苦勞人的宿命" },
      { "id": "8-7", "name": "計畫啟動" },
      { "id": "8-8", "name": "抹殺目擊者" },
      { "id": "8-8 free", "name": "矮人的茶會" },
      { "id": "8-9", "name": "矮人國的信使" },
      { "id": "8-10", "name": "追擊部隊" },
      { "id": "8-11", "name": "攔截跟摧毀" },
      { "id": "8-11 free", "name": "帝國的茶會" },
      { "id": "8-12", "name": "公主與馴養" },
      { "id": "8-13", "name": "有用的跟沒用的" },
      { "id": "8-14", "name": "值得信賴的盟友" },
      { "id": "8-15", "name": "不懂回報是敵人" },
      { "id": "8-16", "name": "敵人的下場" },
      { "id": "8-17", "name": "友好的茶會" },
      { "id": "8-17 free", "name": "異國的茶會" },
      { "id": "8-18", "name": "趕盡殺絕" },
      { "id": "8-19", "name": "與公主連結" }
    ]
  },
  {
    "chapter": "9",
    "name": "第九章：時光醞釀的濃醇香",
    "stages": [
      { "id": "9-2", "name": "進軍！魔王巴爾" },
      { "id": "9-3", "name": "精靈，巴爾來囉" },
      { "id": "9-4", "name": "精靈王賽露西亞" },
      { "id": "9-4 free", "name": "精靈的塵封倉庫" },
      { "id": "9-5", "name": "逐漸進逼的魔族" },
      { "id": "9-6", "name": "巴爾的真本事" },
      { "id": "9-7", "name": "高速資金調度" },
      { "id": "9-8", "name": "精靈大採買" },
      { "id": "9-8 free", "name": "精靈的狩獵倉庫" },
      { "id": "9-9", "name": "逐漸進逼的絕望" },
      { "id": "9-10", "name": "同胞情誼" },
      { "id": "9-11", "name": "擅自出擊的精靈" },
      { "id": "9-12", "name": "精靈王的決意" },
      { "id": "9-12 free", "name": "精靈的珍品倉庫" },
      { "id": "9-13", "name": "深夜的騷動" },
      { "id": "9-14", "name": "無謀的偷襲" },
      { "id": "9-15", "name": "一切盡在計畫內" },
      { "id": "9-16", "name": "捕獲，更多人質" },
      { "id": "9-17", "name": "精靈的孤注一擲" }
    ]
  },
  {
    "chapter": "10",
    "name": "第十章：來去陰陽寮住一晚",
    "stages": [
      { "id": "10-2", "name": "東側的國度" },
      { "id": "10-3", "name": "烈日國觀光手冊" },
      { "id": "10-4", "name": "旅行的準備" },
      { "id": "10-5", "name": "東遊記" },
      { "id": "10-6", "name": "在山林之間" },
      { "id": "10-7", "name": "隱蔽的結界" },
      { "id": "10-8", "name": "魔王喧嘩" },
      { "id": "10-9", "name": "激烈的野戰" },
      { "id": "10-9 free", "name": "藥材之屋" },
      { "id": "10-10", "name": "結界之內" },
      { "id": "10-11", "name": "令人驚訝的衝突" },
      { "id": "10-12", "name": "絕望的力量差" },
      { "id": "10-12 free", "name": "儀式之屋" },
      { "id": "10-13", "name": "陰陽師的決定" },
      { "id": "10-14", "name": "瀕臨極限的結界" },
      { "id": "10-15", "name": "伊布力斯的秘招" },
      { "id": "10-16", "name": "妖狐與魔王SP" },
      { "id": "10-16 free", "name": "劇毒之屋" },
      { "id": "10-17", "name": "魔王的威壓" },
      { "id": "10-18", "name": "陰陽眾的覺悟" },
      { "id": "10-19", "name": "靜的援軍" }
    ]
  },
  {
    "chapter": "11",
    "name": "第十一章：魔與人偶有摩擦",
    "stages": [
      { "id": "11-2", "name": "最前線的戰報" },
      { "id": "11-3", "name": "持續擴大的戰事" },
      { "id": "11-3 free", "name": "湖畔的殘破小屋" },
      { "id": "11-4", "name": "命令" },
      { "id": "11-5", "name": "是鳥身女妖？" },
      { "id": "11-6", "name": "是魔法師？" },
      { "id": "11-7", "name": "不，是KS-Ⅷ" },
      { "id": "11-7 free", "name": "獅鷲爭鬥現場" },
      { "id": "11-8", "name": "不速之客" },
      { "id": "11-9", "name": "混亂的戰局" },
      { "id": "11-10", "name": "情報衝擊" },
      { "id": "11-11", "name": "斬首行動？" },
      { "id": "11-12", "name": "公主間的情誼" },
      { "id": "11-12 free", "name": "湖畔的獵人小屋" },
      { "id": "11-13", "name": "法斯軍的騷動" },
      { "id": "11-14", "name": "西線無戰事" },
      { "id": "11-14 free", "name": "倒塌的巨樹" },
      { "id": "11-15", "name": "獵人？獵物？" },
      { "id": "11-16", "name": "法斯的偵查部隊" },
      { "id": "11-17", "name": "遠方衝突" },
      { "id": "11-18", "name": "果斷撤退" },
      { "id": "11-19", "name": "魔與人偶有摩擦" }
    ]
  },
  {
    "chapter": "12",
    "name": "第十二章：攻守兼備大將軍",
    "stages": [
      { "id": "12-2", "name": "美女與野戰" },
      { "id": "12-3", "name": "行軍" },
      { "id": "12-4", "name": "多種族混合戰線" },
      { "id": "12-4 free", "name": "魔界的補給" },
      { "id": "12-5", "name": "互相試探" },
      { "id": "12-6", "name": "朱諾安的評估" },
      { "id": "12-7", "name": "勢均力敵" },
      { "id": "12-7 free", "name": "矮人國的補給" },
      { "id": "12-8", "name": "新的友誼" },
      { "id": "12-9", "name": "迷途的軍隊" },
      { "id": "12-10", "name": "殺出重圍" },
      { "id": "12-10 free", "name": "精靈國的補給" },
      { "id": "12-11", "name": "伊布力斯的分析" },
      { "id": "12-12", "name": "決勝之日!" },
      { "id": "12-13", "name": "熱烈歡迎" },
      { "id": "12-13 free", "name": "襲擊法斯補給線" },
      { "id": "12-14", "name": "連環爆" },
      { "id": "12-15", "name": "人算不如天算" },
      { "id": "12-15 free", "name": "攻擊珍妮的村莊" },
      { "id": "12-16", "name": "小麻煩" },
      { "id": "12-17", "name": "風向變化" }
    ]
  },
  {
    "chapter": "13",
    "name": "第十三章：霸道劍聖不想輸",
    "stages": [
      { "id": "13-2", "name": "第一劍聖" },
      { "id": "13-3", "name": "僵持的戰線" },
      { "id": "13-4", "name": "年長者" },
      { "id": "13-5", "name": "拖延戰術" },
      { "id": "13-6", "name": "遲滯打法" },
      { "id": "13-7", "name": "戰前祭品" },
      { "id": "13-7 free", "name": "荒地獸群" },
      { "id": "13-8", "name": "列陣" },
      { "id": "13-9", "name": "出擊" },
      { "id": "13-10", "name": "自負與自傲" },
      { "id": "13-11", "name": "魔王與劍聖" },
      { "id": "13-12", "name": "高手對決" },
      { "id": "13-13", "name": "樂趣" },
      { "id": "13-13 free", "name": "隱藏的寶藏" },
      { "id": "13-14", "name": "勝負之日" },
      { "id": "13-15", "name": "赴約" },
      { "id": "13-16", "name": "戰場衝突" },
      { "id": "13-17", "name": "世事無常" },
      { "id": "13-17 free", "name": "儀式之地" },
      { "id": "13-18", "name": "勝利的突襲" },
      { "id": "13-19", "name": "期待與失望" }
    ]
  },
  {
    "chapter": "14",
    "name": "第十四章：在烈日國說晚安",
    "stages": [
      { "id": "14-2", "name": "警告" },
      { "id": "14-3", "name": "誘餌" },
      { "id": "14-4", "name": "城內一隅" },
      { "id": "14-5", "name": "奇襲" },
      { "id": "14-6", "name": "命運" },
      { "id": "14-7", "name": "兵臨城下" },
      { "id": "14-7 free", "name": "大蛇的藏身處" },
      { "id": "14-8", "name": "凜月之願" },
      { "id": "14-9", "name": "陽動作戰" },
      { "id": "14-10", "name": "十死無生" },
      { "id": "14-11", "name": "襲營" },
      { "id": "14-12", "name": "亂" },
      { "id": "14-12 free", "name": "被封印的書庫" },
      { "id": "14-13", "name": "忍術撤退之術" },
      { "id": "14-14", "name": "背棄信條之人" },
      { "id": "14-15", "name": "掙扎" },
      { "id": "14-16", "name": "信念" },
      { "id": "14-17", "name": "晚安，公主殿下" },
      { "id": "14-17 free", "name": "毒蜘蛛的窩" },
      { "id": "14-18", "name": "凜月的抉擇" },
      { "id": "14-19", "name": "友誼與堅持" }
    ]
  },
  {
    "chapter": "15",
    "name": "第十五章：正義從天而降",
    "stages": [
      { "id": "15-2", "name": "禱告與神蹟" },
      { "id": "15-2 free", "name": "史萊姆獵場" },
      { "id": "15-3", "name": "天使參戰！！" },
      { "id": "15-4", "name": "局勢的變動" },
      { "id": "15-5", "name": "牽制" },
      { "id": "15-6", "name": "意外訪客" },
      { "id": "15-6 free", "name": "導電測試處" },
      { "id": "15-7", "name": "風雲變色" },
      { "id": "15-8", "name": "撤退的勇氣" },
      { "id": "15-9", "name": "責任與器量" },
      { "id": "15-9 free", "name": "藤蔓的早露" },
      { "id": "15-10", "name": "執行戰術" },
      { "id": "15-11", "name": "消耗戰" },
      { "id": "15-12", "name": "一團泥淖" },
      { "id": "15-12 free", "name": "觸手實驗室" },
      { "id": "15-13", "name": "威力偵查" },
      { "id": "15-14", "name": "信仰之力" },
      { "id": "15-15", "name": "釣魚" },
      { "id": "15-15 free", "name": "淫蟲與粉塵" },
      { "id": "15-16", "name": "前進的道路" },
      { "id": "15-17", "name": "時代終結" }
    ]
  },
  {
    "chapter": "16",
    "name": "第十六章：擅長權衡的軍師大人",
    "stages": [
      { "id": "16-2", "name": "最適當的戰場" },
      { "id": "16-2 free", "name": "毒熊之森" },
      { "id": "16-3", "name": "不安與監視" },
      { "id": "16-4", "name": "戰場的佈置" },
      { "id": "16-5", "name": "布蘭妮的邀約" },
      { "id": "16-5 free", "name": "巨鳥湖畔" },
      { "id": "16-6", "name": "原地駐紮" },
      { "id": "16-7", "name": "待命" },
      { "id": "16-8", "name": "前往大橋" },
      { "id": "16-9", "name": "布蘭妮之謀" },
      { "id": "16-9 free", "name": "獅鷲平原" },
      { "id": "16-10", "name": "背叛？" },
      { "id": "16-11", "name": "肅清行動" },
      { "id": "16-12", "name": "欺上瞞下" },
      { "id": "16-13", "name": "大橋攻防戰" },
      { "id": "16-13 free", "name": "濁溪礦坑" },
      { "id": "16-14", "name": "陣勢變換" },
      { "id": "16-15", "name": "實力的展現" },
      { "id": "16-16", "name": "點到為止" },
      { "id": "16-17", "name": "圓滿的收尾" }
    ]
  },
  {
    "chapter": "17",
    "name": "第十七章：勇者鬥魔族",
    "stages": [
      { "id": "17-2", "name": "勇者的指導課" },
      { "id": "17-2 free", "name": "狩獵之村" },
      { "id": "17-3", "name": "追捕烏魯塔" },
      { "id": "17-4", "name": "魔族進軍" },
      { "id": "17-5", "name": "抵抗" },
      { "id": "17-5 free", "name": "鍛造之村" },
      { "id": "17-6", "name": "鄉民衝突" },
      { "id": "17-7", "name": "戰爭稅" },
      { "id": "17-8", "name": "徵稅部隊" },
      { "id": "17-9", "name": "旅人" },
      { "id": "17-9 free", "name": "祭祀之村" },
      { "id": "17-10", "name": "敗走傭兵" },
      { "id": "17-11", "name": "侵略的魔族" },
      { "id": "17-12", "name": "魔族營地" },
      { "id": "17-13", "name": "好與壞" },
      { "id": "17-13 free", "name": "煉金之村" },
      { "id": "17-14", "name": "演習準備" },
      { "id": "17-15", "name": "暖身運動" },
      { "id": "17-16", "name": "演習作戰" },
      { "id": "17-17", "name": "被玩弄的烏魯塔" },
      { "id": "17-17 free", "name": "燃燒的高塔" },
      { "id": "17-18", "name": "決勝點" }
    ]
  },
  {
    "chapter": "18",
    "name": "第十八章：特裝魔導進化戰記",
    "stages": [
      { "id": "18-2", "name": "迷惘的勇者" },
      { "id": "18-2 free", "name": "研究素材：爪" },
      { "id": "18-3", "name": "賢者的補償" },
      { "id": "18-4", "name": "賢者的指導" },
      { "id": "18-5", "name": "試作機改造" },
      { "id": "18-5 free", "name": "研究素材：鐵" },
      { "id": "18-6", "name": "機械兵團" },
      { "id": "18-7", "name": "紀錄影像" },
      { "id": "18-8", "name": "投資的價值" },
      { "id": "18-8 free", "name": "研究素材：水" },
      { "id": "18-9", "name": "戰線" },
      { "id": "18-10", "name": "撒旦軍勢" },
      { "id": "18-11", "name": "兵器的試探" },
      { "id": "18-11 free", "name": "研究素材：液" },
      { "id": "18-12", "name": "研究者的邀約" },
      { "id": "18-13", "name": "導航" },
      { "id": "18-14", "name": "最高傑作" },
      { "id": "18-14 free", "name": "研究素材：粉" },
      { "id": "18-15", "name": "餘興節目" },
      { "id": "18-16", "name": "撒旦愉悅之日" }
    ]
  },
  {
    "chapter": "19",
    "name": "第十九章：海的另一端都是敵人",
    "stages": [
      { "id": "19-2", "name": "皇帝召見" },
      { "id": "19-3", "name": "愚蠢之王" },
      { "id": "19-4", "name": "逃亡的近衛" },
      { "id": "19-5", "name": "撤軍" },
      { "id": "19-6", "name": "獵犬獠牙" },
      { "id": "19-6 free", "name": "殘屋" },
      { "id": "19-7", "name": "異國的侵攻" },
      { "id": "19-8", "name": "狂妄廝殺" },
      { "id": "19-9", "name": "鎮壓完畢" },
      { "id": "19-10", "name": "清查設施" },
      { "id": "19-11", "name": "搜刮戰利品" },
      { "id": "19-12", "name": "魔族進軍" },
      { "id": "19-12 free", "name": "壞壁" },
      { "id": "19-13", "name": "不平靜的海岸" },
      { "id": "19-14", "name": "斥侯探查" },
      { "id": "19-15", "name": "斷訊" },
      { "id": "19-16", "name": "遺留訊息" },
      { "id": "19-17", "name": "魔族的弱點" },
      { "id": "19-18", "name": "故布疑陣" },
      { "id": "19-18 free", "name": "絕路" },
      { "id": "19-19", "name": "知而不知" },
      { "id": "19-20", "name": "使者" }
    ]
  },
  {
    "chapter": "20",
    "name": "第二十章：神田綾音的憂鬱",
    "stages": [
      { "id": "20-2", "name": "修練木樁" },
      { "id": "20-3", "name": "活下來的準備" },
      { "id": "20-4", "name": "神田綾音的迷惘" },
      { "id": "20-5", "name": "劫掠軍" },
      { "id": "20-6", "name": "山賊" },
      { "id": "20-7", "name": "混亂行軍" },
      { "id": "20-8", "name": "小趣事" },
      { "id": "20-8 free", "name": "矮人軍歌" },
      { "id": "20-9", "name": "神田綾音的憂鬱" },
      { "id": "20-10", "name": "練習場" },
      { "id": "20-11", "name": "檯面下的陰謀" },
      { "id": "20-11 free", "name": "法斯流亡軍" },
      { "id": "20-12", "name": "矮人風範" },
      { "id": "20-13", "name": "矮人戰法" },
      { "id": "20-14", "name": "士氣低迷" },
      { "id": "20-14 free", "name": "一團散沙" },
      { "id": "20-15", "name": "存活的方法" },
      { "id": "20-16", "name": "逃命的方法" },
      { "id": "20-17", "name": "初次交鋒" },
      { "id": "20-18", "name": "缺口突入" },
      { "id": "20-19", "name": "神田綾音的信念" },
      { "id": "20-20", "name": "河谷鎮激戰" },
      { "id": "20-21", "name": "神田綾音的選擇" }
    ]
  },
  {
    "chapter": "21",
    "name": "第二十一章：前進吧！勇者大人",
    "stages": [
      { "id": "21-2", "name": "些許喘息" },
      { "id": "21-3", "name": "傳說中的賢者" },
      { "id": "21-3 free", "name": "地下室" },
      { "id": "21-4", "name": "迷霧之森" },
      { "id": "21-5", "name": "森之結界" },
      { "id": "21-6", "name": "短暫的幸福" },
      { "id": "21-6 free", "name": "儲藏室" },
      { "id": "21-7", "name": "訪客" },
      { "id": "21-8", "name": "結界崩壞" },
      { "id": "21-8 free", "name": "原料室" },
      { "id": "21-9", "name": "幻象法術" },
      { "id": "21-10", "name": "森中魔物" },
      { "id": "21-11", "name": "無力的勇者" },
      { "id": "21-11 free", "name": "藥劑室" },
      { "id": "21-12", "name": "騷動的森林" },
      { "id": "21-13", "name": "暴走魔獸" },
      { "id": "21-14", "name": "前進吧！勇者" },
      { "id": "21-14 free", "name": "垃圾場" },
      { "id": "21-15", "name": "平息騷動" },
      { "id": "21-16", "name": "回歸寂靜" },
      { "id": "21-17", "name": "遠方草原" },
      { "id": "21-18", "name": "壕溝戰" },
      { "id": "21-19", "name": "陣前逃亡" },
      { "id": "21-20", "name": "港口要塞" }
    ]
  }
]
